JarvisAI/__init__.py
JarvisAI/features_manager.py
JarvisAI/brain/__init__.py
JarvisAI/brain/auth.py
JarvisAI/brain/chatbot_premium.py
JarvisAI/brain/intent_classification.py
JarvisAI/brain/ner.py
JarvisAI/features/__init__.py
JarvisAI/features/click_photo.py
JarvisAI/features/covid_cases.py
JarvisAI/features/date_time.py
JarvisAI/features/games.py
JarvisAI/features/greet.py
JarvisAI/features/iambored.py
JarvisAI/features/internet_speed_test.py
JarvisAI/features/joke.py
JarvisAI/features/news.py
JarvisAI/features/places_near_me.py
JarvisAI/features/screenshot.py
JarvisAI/features/send_email.py
JarvisAI/features/tell_me_about.py
JarvisAI/features/volume_controller.py
JarvisAI/features/weather.py
JarvisAI/features/website_open.py
JarvisAI/features/whatsapp_message.py
JarvisAI/features/youtube_play.py
JarvisAI/features/youtube_video_downloader.py
JarvisAI/utils/__init__.py
JarvisAI/utils/input_output.py
JarvisAI/utils/speech_to_text/__init__.py
JarvisAI/utils/speech_to_text/speech_to_text.py
JarvisAI/utils/speech_to_text/speech_to_text_whisper.py
JarvisAI/utils/text_to_speech/__init__.py
JarvisAI/utils/text_to_speech/text_to_speech.py
JarvisAI-4.9.dist-info/License.txt
JarvisAI-4.9.dist-info/METADATA
JarvisAI-4.9.dist-info/WHEEL
JarvisAI-4.9.dist-info/top_level.txt
JarvisAI-4.9.dist-info/RECORD
