Metadata-Version: 2.1
Name: JarvisAI
Version: 4.9
Summary: JarvisAI is python library to build your own AI virtual assistant with natural language processing.
Home-page: https://github.com/Dipeshpal/Jarvis_AI
Author: Dipesh
Author-email: dipeshpal17@gmail.com
License: UNKNOWN
Project-URL: Official Website, https://jarvisai.in
Project-URL: Documentation, https://github.com/Dipeshpal/Jarvis_AI
Project-URL: Donate, https://www.buymeacoffee.com/dipeshpal
Project-URL: Say Thanks!, https://youtube.com/techportofficial
Project-URL: Source, https://github.com/Dipeshpal/Jarvis_AI
Project-URL: Contact, https://www.dipeshpal.in/social
Platform: UNKNOWN
Classifier: Programming Language :: Python :: 3
Classifier: License :: OSI Approved :: MIT License
Classifier: Operating System :: OS Independent
Requires-Python: >=3.6
License-File: License.txt
Requires-Dist: numpy
Requires-Dist: gtts
Requires-Dist: playsound
Requires-Dist: pyscreenshot
Requires-Dist: opencv-python
Requires-Dist: SpeechRecognition
Requires-Dist: pyjokes
Requires-Dist: wikipedia
Requires-Dist: scipy
Requires-Dist: lazyme
Requires-Dist: requests
Requires-Dist: pyttsx3
Requires-Dist: spacy (==3.5.0)
Requires-Dist: pywhatkit
Requires-Dist: speedtest-cli
Requires-Dist: pytube
Requires-Dist: pycountry
Requires-Dist: pyaudio
Requires-Dist: mediapipe (==0.8.11)
Requires-Dist: pycaw
Requires-Dist: openai-whisper
Requires-Dist: shutup
Requires-Dist: sounddevice
Requires-Dist: html2text (==2020.1.16)
Requires-Dist: wikipedia (==1.4.0)
Requires-Dist: Markdown (==3.4.1)
Requires-Dist: markdown2 (==2.4.8)
Requires-Dist: lxml (==4.9.2)
Requires-Dist: googlesearch-python (==1.2.3)
Requires-Dist: selenium
Requires-Dist: selenium-pro
Requires-Dist: element-manager
